etlhelper/__init__.py
etlhelper/abort.py
etlhelper/connect.py
etlhelper/db_helper_factory.py
etlhelper/db_params.py
etlhelper/etl.py
etlhelper/exceptions.py
etlhelper/row_factories.py
etlhelper/types.py
etlhelper/utils.py
etlhelper/db_helpers/__init__.py
etlhelper/db_helpers/db_helper.py
etlhelper/db_helpers/mssql.py
etlhelper/db_helpers/oracle.py
etlhelper/db_helpers/postgres.py
etlhelper/db_helpers/sqlite.py
etlhelper-1.0.2.dist-info/LICENSE
etlhelper-1.0.2.dist-info/METADATA
etlhelper-1.0.2.dist-info/WHEEL
etlhelper-1.0.2.dist-info/top_level.txt
etlhelper-1.0.2.dist-info/RECORD
