Metadata-Version: 2.1
Name: etlhelper
Version: 1.0.2
Summary: etlhelper is Python ETL library to simplify data transfer into and out of databases.
Author-email: BGS Informatics <enquiries@bgs.ac.uk>
License: LGPL-3.0 license
Project-URL: Source Code, https://github.com/BritishGeologicalSurvey/etlhelper
Project-URL: Documentation, https://britishgeologicalsurvey.github.io/etlhelper/
Classifier: Development Status :: 5 - Production/Stable
Classifier: Intended Audience :: Developers
Classifier: Intended Audience :: Information Technology
Classifier: Intended Audience :: Science/Research
Classifier: License :: OSI Approved :: GNU Lesser General Public License v3 or later (LGPLv3+)
Classifier: Natural Language :: English
Classifier: Operating System :: OS Independent
Classifier: Programming Language :: Python :: 3
Classifier: Topic :: Database
Classifier: Topic :: Scientific/Engineering :: GIS
Requires-Python: >=3.9
License-File: LICENSE
Provides-Extra: oracle
Requires-Dist: oracledb; extra == "oracle"
Requires-Dist: cffi; extra == "oracle"
Provides-Extra: mssql
Requires-Dist: pyodbc; extra == "mssql"
Provides-Extra: postgres
Requires-Dist: psycopg2-binary; extra == "postgres"
Provides-Extra: all
Requires-Dist: oracledb; extra == "all"
Requires-Dist: cffi; extra == "all"
Requires-Dist: pyodbc; extra == "all"
Requires-Dist: psycopg2-binary; extra == "all"
Provides-Extra: dev
Requires-Dist: flake8; extra == "dev"
Requires-Dist: ipdb; extra == "dev"
Requires-Dist: ipython; extra == "dev"
Requires-Dist: pytest; extra == "dev"
Requires-Dist: pytest-cov; extra == "dev"
Provides-Extra: pkg
Requires-Dist: build; extra == "pkg"
Requires-Dist: twine; extra == "pkg"
